{"id": "5f372777-c41f-422c-a2f3-fb7a5172d1ad", "name": null, "timestamp": "2025-12-19T00:53:53.601642", "metadata": {}, "tags": [], "suite": {"metrics": [{"type": "evidently.metrics.data_integrity.dataset_summary_metric.DatasetSummaryMetric", "options": {"color": null, "render": null, "custom": {}, "data_definition": null}, "almost_duplicated_threshold": 0.95, "almost_constant_threshold": 0.95}, {"type": "evidently.metrics.data_integrity.column_summary_metric.ColumnSummaryMetric", "options": {"color": null, "render": null, "custom": {}, "data_definition": null}, "column_name": {"type": "evidently.base_metric.ColumnName", "name": "user_input", "display_name": "user_input", "dataset": "main"}}, {"type": "evidently.metrics.data_integrity.column_summary_metric.ColumnSummaryMetric", "options": {"color": null, "render": null, "custom": {}, "data_definition": null}, "column_name": {"type": "evidently.base_metric.ColumnName", "name": "response", "display_name": "response", "dataset": "main"}}, {"type": "evidently.metrics.data_integrity.column_summary_metric.ColumnSummaryMetric", "options": {"color": null, "render": null, "custom": {}, "data_definition": null}, "column_name": {"type": "evidently.base_metric.ColumnName", "name": "input_length", "display_name": "input_length", "dataset": "main"}}, {"type": "evidently.metrics.data_integrity.column_summary_metric.ColumnSummaryMetric", "options": {"color": null, "render": null, "custom": {}, "data_definition": null}, "column_name": {"type": "evidently.base_metric.ColumnName", "name": "response_length", "display_name": "response_length", "dataset": "main"}}, {"type": "evidently.metrics.data_integrity.column_summary_metric.ColumnSummaryMetric", "options": {"color": null, "render": null, "custom": {}, "data_definition": null}, "column_name": {"type": "evidently.base_metric.ColumnName", "name": "feedback", "display_name": "feedback", "dataset": "main"}}], "metric_results": [{"type": "evidently.metrics.data_integrity.dataset_summary_metric.DatasetSummaryMetricResult", "almost_duplicated_threshold": 0.95, "current": {"type": "evidently.metrics.data_integrity.dataset_summary_metric.DatasetSummary", "target": null, "prediction": null, "date_column": null, "id_column": null, "number_of_columns": 6, "number_of_rows": 1, "number_of_missing_values": 0, "number_of_categorical_columns": 4, "number_of_numeric_columns": 2, "number_of_text_columns": 0, "number_of_datetime_columns": 0, "number_of_constant_columns": 6, "number_of_almost_constant_columns": 6, "number_of_duplicated_columns": 0, "number_of_almost_duplicated_columns": 0, "number_of_empty_rows": 0, "number_of_empty_columns": 0, "number_of_duplicated_rows": 0, "columns_type_data": {"user_input": {"dtype": "object"}, "response": {"dtype": "object"}, "timestamp": {"dtype": "object"}, "input_length": {"dtype": "int64"}, "response_length": {"dtype": "int64"}, "feedback": {"dtype": "object"}}, "nans_by_columns": {"user_input": 0, "response": 0, "timestamp": 0, "input_length": 0, "response_length": 0, "feedback": 0}, "number_uniques_by_columns": {"user_input": 1, "response": 1, "timestamp": 1, "input_length": 1, "response_length": 1, "feedback": 1}}, "reference": null}, {"type": "evidently.metrics.data_integrity.column_summary_metric.ColumnSummaryResult", "column_name": "user_input", "column_type": "cat", "reference_characteristics": null, "current_characteristics": {"type": "evidently.metrics.data_integrity.column_summary_metric.CategoricalCharacteristics", "number_of_rows": 1, "count": 1, "missing": 0, "missing_percentage": 0.0, "unique": 1, "unique_percentage": 100.0, "most_common": "reset pass", "most_common_percentage": 100.0, "new_in_current_values_count": null, "unused_in_current_values_count": null}, "plot_data": {"type": "evidently.metrics.data_integrity.column_summary_metric.DataQualityPlot", "bins_for_hist": {"type": "evidently.metric_results.Histogram", "current": {"type": "evidently.metric_results.HistogramData", "x": ["reset pass"], "count": [1], "name": null}, "reference": null, "current_log": null, "reference_log": null}, "data_in_time": null, "data_by_target": null, "counts_of_values": {"current": {"x": {"0": "reset pass"}, "count": {"0": 1}}}}}, {"type": "evidently.metrics.data_integrity.column_summary_metric.ColumnSummaryResult", "column_name": "response", "column_type": "cat", "reference_characteristics": null, "current_characteristics": {"type": "evidently.metrics.data_integrity.column_summary_metric.CategoricalCharacteristics", "number_of_rows": 1, "count": 1, "missing": 0, "missing_percentage": 0.0, "unique": 1, "unique_percentage": 100.0, "most_common": "For password reset, please contact the IT Help Desk immediately at **(555) 234-5600**. They will assist you with resetting your password securely.\n\n**Before calling, please have ready:**\n- Your employee ID or username\n- A form of identification\n- The specific system you need access to (EHR, email, etc.)\n\n**Important notes:**\n- For security and compliance reasons, passwords cannot be reset through this chat\n- Clinical staff receive priority support for urgent access needs\n- The Help Desk will verify your identity before proceeding with any password changes\n\nIf you're experiencing login issues but believe your password is correct, this may be an authentication problem rather than needing a password reset. In that case, avoid repeated login attempts (which can lock your account) and contact the Help Desk right away.\n\nIs there anything else I can help clarify about the password reset process?", "most_common_percentage": 100.0, "new_in_current_values_count": null, "unused_in_current_values_count": null}, "plot_data": {"type": "evidently.metrics.data_integrity.column_summary_metric.DataQualityPlot", "bins_for_hist": {"type": "evidently.metric_results.Histogram", "current": {"type": "evidently.metric_results.HistogramData", "x": ["For password reset, please contact the IT Help Desk immediately at **(555) 234-5600**. They will assist you with resetting your password securely.\n\n**Before calling, please have ready:**\n- Your employee ID or username\n- A form of identification\n- The specific system you need access to (EHR, email, etc.)\n\n**Important notes:**\n- For security and compliance reasons, passwords cannot be reset through this chat\n- Clinical staff receive priority support for urgent access needs\n- The Help Desk will verify your identity before proceeding with any password changes\n\nIf you're experiencing login issues but believe your password is correct, this may be an authentication problem rather than needing a password reset. In that case, avoid repeated login attempts (which can lock your account) and contact the Help Desk right away.\n\nIs there anything else I can help clarify about the password reset process?"], "count": [1], "name": null}, "reference": null, "current_log": null, "reference_log": null}, "data_in_time": null, "data_by_target": null, "counts_of_values": {"current": {"x": {"0": "For password reset, please contact the IT Help Desk immediately at **(555) 234-5600**. They will assist you with resetting your password securely.\n\n**Before calling, please have ready:**\n- Your employee ID or username\n- A form of identification\n- The specific system you need access to (EHR, email, etc.)\n\n**Important notes:**\n- For security and compliance reasons, passwords cannot be reset through this chat\n- Clinical staff receive priority support for urgent access needs\n- The Help Desk will verify your identity before proceeding with any password changes\n\nIf you're experiencing login issues but believe your password is correct, this may be an authentication problem rather than needing a password reset. In that case, avoid repeated login attempts (which can lock your account) and contact the Help Desk right away.\n\nIs there anything else I can help clarify about the password reset process?"}, "count": {"0": 1}}}}}, {"type": "evidently.metrics.data_integrity.column_summary_metric.ColumnSummaryResult", "column_name": "input_length", "column_type": "cat", "reference_characteristics": null, "current_characteristics": {"type": "evidently.metrics.data_integrity.column_summary_metric.CategoricalCharacteristics", "number_of_rows": 1, "count": 1, "missing": 0, "missing_percentage": 0.0, "unique": 1, "unique_percentage": 100.0, "most_common": 10, "most_common_percentage": 100.0, "new_in_current_values_count": null, "unused_in_current_values_count": null}, "plot_data": {"type": "evidently.metrics.data_integrity.column_summary_metric.DataQualityPlot", "bins_for_hist": {"type": "evidently.metric_results.Histogram", "current": {"type": "evidently.metric_results.HistogramData", "x": ["10"], "count": [1], "name": null}, "reference": null, "current_log": null, "reference_log": null}, "data_in_time": null, "data_by_target": null, "counts_of_values": {"current": {"x": {"0": 10}, "count": {"0": 1}}}}}, {"type": "evidently.metrics.data_integrity.column_summary_metric.ColumnSummaryResult", "column_name": "response_length", "column_type": "cat", "reference_characteristics": null, "current_characteristics": {"type": "evidently.metrics.data_integrity.column_summary_metric.CategoricalCharacteristics", "number_of_rows": 1, "count": 1, "missing": 0, "missing_percentage": 0.0, "unique": 1, "unique_percentage": 100.0, "most_common": 901, "most_common_percentage": 100.0, "new_in_current_values_count": null, "unused_in_current_values_count": null}, "plot_data": {"type": "evidently.metrics.data_integrity.column_summary_metric.DataQualityPlot", "bins_for_hist": {"type": "evidently.metric_results.Histogram", "current": {"type": "evidently.metric_results.HistogramData", "x": ["901"], "count": [1], "name": null}, "reference": null, "current_log": null, "reference_log": null}, "data_in_time": null, "data_by_target": null, "counts_of_values": {"current": {"x": {"0": 901}, "count": {"0": 1}}}}}, {"type": "evidently.metrics.data_integrity.column_summary_metric.ColumnSummaryResult", "column_name": "feedback", "column_type": "cat", "reference_characteristics": null, "current_characteristics": {"type": "evidently.metrics.data_integrity.column_summary_metric.CategoricalCharacteristics", "number_of_rows": 1, "count": 1, "missing": 0, "missing_percentage": 0.0, "unique": 1, "unique_percentage": 100.0, "most_common": "no_feedback", "most_common_percentage": 100.0, "new_in_current_values_count": null, "unused_in_current_values_count": null}, "plot_data": {"type": "evidently.metrics.data_integrity.column_summary_metric.DataQualityPlot", "bins_for_hist": {"type": "evidently.metric_results.Histogram", "current": {"type": "evidently.metric_results.HistogramData", "x": ["no_feedback"], "count": [1], "name": null}, "reference": null, "current_log": null, "reference_log": null}, "data_in_time": null, "data_by_target": null, "counts_of_values": {"current": {"x": {"0": "no_feedback"}, "count": {"0": 1}}}}}], "tests": [], "test_results": [], "options": {"color": null, "render": null, "custom": {}, "data_definition": null}, "data_definition": {"columns": {"response": {"column_name": "response", "column_type": "cat"}, "input_length": {"column_name": "input_length", "column_type": "cat"}, "response_length": {"column_name": "response_length", "column_type": "cat"}, "user_input": {"column_name": "user_input", "column_type": "cat"}, "feedback": {"column_name": "feedback", "column_type": "cat"}, "timestamp": {"column_name": "timestamp", "column_type": "cat"}}, "target": null, "prediction_columns": null, "id_column": null, "datetime_column": null, "embeddings": null, "user_id": null, "item_id": null, "task": null, "classification_labels": null, "reference_present": false, "recommendations_type": "score"}, "run_metadata": {"descriptors": {}}}, "metrics_ids": [0, 1, 2, 3, 4, 5], "test_ids": [], "options": {"color": null, "render": null, "custom": {}, "data_definition": null}, "links": {"datasets": {"input": {"reference": null, "current": null, "additional": {}}, "output": {"reference": null, "current": null, "additional": {}}}}}